aiohttp_light_utils/connections.py
aiohttp_light_utils/exceptions.py
aiohttp_light_utils/log.py
aiohttp_light_utils/settings.py
aiohttp_light_utils/types.py
aiohttp_light_utils/views.py
aiohttp_light_utils-0.2.9.dist-info/WHEEL
aiohttp_light_utils-0.2.9.dist-info/METADATA
aiohttp_light_utils-0.2.9.dist-info/RECORD
